[
    {
        "name": "TruyenQQ",
        "id": 837201455,
        "baseUrl": "https://truyenqqko.com",
        "lang": "vi",
        "typeSource": "single",
        "iconUrl": "https://www.google.com/s2/favicons?sz=128&domain=https://truyenqqko.com",
        "dateFormat": "",
        "dateFormatLocale": "",
        "isNsfw": false,
        "hasCloudflare": false,
        "sourceCodeUrl": "https://raw.githubusercontent.com/vuongvan/mangayomi-swak-extensions/refs/heads/main/javascript/manga/src/vi/truyenqq.js",
        "apiUrl": "",
        "version": "1.0.0",
        "isManga": true,
        "itemType": 0,
        "isFullData": false,
        "appMinVerReq": "0.5.0",
        "additionalParams": "",
        "sourceCodeLanguage": 1,
        "notes": ""
    },
    {
        "name": "Atsumaru",
        "id": 2829806388,
        "baseUrl": "https://atsu.moe",
        "lang": "en",
        "typeSource": "single",
        "iconUrl": "https://www.google.com/s2/favicons?sz=256&domain=https://atsu.moe",
        "dateFormat": "",
        "dateFormatLocale": "",
        "isNsfw": false,
        "hasCloudflare": false,
        "sourceCodeUrl": "https://raw.githubusercontent.com/vuongvan/mangayomi-swak-extensions/refs/heads/main/javascript/manga/src/en/atsumaru.js",
        "apiUrl": "",
        "version": "0.0.1",
        "isManga": true,
        "itemType": 0,
        "isFullData": false,
        "appMinVerReq": "0.5.0",
        "additionalParams": "",
        "sourceCodeLanguage": 1,
        "notes": ""
    },
    {
        "name": "Mangapark",
        "id": 2302366102,
        "baseUrl": "https://mangapark.io",
        "lang": "en",
        "typeSource": "single",
        "iconUrl": "https://www.google.com/s2/favicons?sz=256&domain=https://mangapark.io",
        "dateFormat": "",
        "dateFormatLocale": "",
        "isNsfw": false,
        "hasCloudflare": false,
        "sourceCodeUrl": "https://raw.githubusercontent.com/vuongvan/mangayomi-swak-extensions/refs/heads/main/javascript/manga/src/en/mangapark.js",
        "apiUrl": "",
        "version": "1.0.1",
        "isManga": true,
        "itemType": 0,
        "isFullData": false,
        "appMinVerReq": "0.5.0",
        "additionalParams": "",
        "sourceCodeLanguage": 1,
        "notes": ""
    },
    {
        "name": "Weeb Central",
        "id": 693275080,
        "baseUrl": "https://weebcentral.com",
        "lang": "en",
        "typeSource": "single",
        "iconUrl": "https://www.google.com/s2/favicons?sz=128&domain=https://weebcentral.com",
        "dateFormat": "",
        "dateFormatLocale": "",
        "isNsfw": false,
        "hasCloudflare": false,
        "sourceCodeUrl": "https://raw.githubusercontent.com/vuongvan/mangayomi-swak-extensions/refs/heads/main/javascript/manga/src/en/weebcentral.js",
        "apiUrl": "",
        "version": "0.1.0",
        "isManga": true,
        "itemType": 0,
        "isFullData": false,
        "appMinVerReq": "0.5.0",
        "additionalParams": "",
        "sourceCodeLanguage": 1,
        "notes": ""
    },
    {
        "name": "Mangapill",
        "id": 960321322,
        "baseUrl": "https://mangapill.com",
        "lang": "en",
        "typeSource": "single",
        "iconUrl": "https://www.google.com/s2/favicons?sz=64&domain=https://mangapill.com/",
        "dateFormat": "",
        "dateFormatLocale": "",
        "isNsfw": false,
        "hasCloudflare": false,
        "sourceCodeUrl": "https://raw.githubusercontent.com/vuongvan/mangayomi-swak-extensions/refs/heads/main/javascript/manga/src/en/mangapill.js",
        "apiUrl": "",
        "version": "1.0.4",
        "isManga": true,
        "itemType": 0,
        "isFullData": false,
        "appMinVerReq": "0.5.0",
        "additionalParams": "",
        "sourceCodeLanguage": 1,
        "notes": ""
    },
    {
        "name": "TruyenQQ",
        "id": 837201455,
        "baseUrl": "https://truyenqqko.com",
        "lang": "vi",
        "typeSource": "single",
        "iconUrl": "https://www.google.com/s2/favicons?sz=128&domain=https://truyenqqko.com",
        "dateFormat": "",
        "dateFormatLocale": "",
        "isNsfw": false,
        "hasCloudflare": false,
        "sourceCodeUrl": "https://raw.githubusercontent.com/vuongvan/mangayomi-swak-extensions/refs/heads/main/javascript/manga/src/vi/truyenqq.js",
        "apiUrl": "",
        "version": "1.0.0",
        "isManga": true,
        "itemType": 0,
        "isFullData": false,
        "appMinVerReq": "0.5.0",
        "additionalParams": "",
        "sourceCodeLanguage": 1,
        "notes": ""
    },
    {
        "name": "ReadComicOnline",
        "id": 376287717,
        "baseUrl": "https://readcomiconline.li",
        "lang": "en",
        "typeSource": "single",
        "iconUrl": "https://www.google.com/s2/favicons?sz=256&domain=https://readcomiconline.li/",
        "dateFormat": "",
        "dateFormatLocale": "",
        "isNsfw": false,
        "hasCloudflare": false,
        "sourceCodeUrl": "https://raw.githubusercontent.com/vuongvan/mangayomi-swak-extensions/refs/heads/main/javascript/manga/src/en/readcomiconline.js",
        "apiUrl": "",
        "version": "0.3.0",
        "isManga": true,
        "itemType": 0,
        "isFullData": false,
        "appMinVerReq": "0.5.0",
        "additionalParams": "",
        "sourceCodeLanguage": 1,
        "notes": ""
    },
    {
        "name": "WeLoMa",
        "id": 1890238687,
        "baseUrl": "https://weloma.art",
        "lang": "ja",
        "typeSource": "single",
        "iconUrl": "https://raw.github.com/Swakshan/mangayomi-swak-extensions/main/javascript/icon/ja.weloma.jpg",
        "dateFormat": "",
        "dateFormatLocale": "",
        "isNsfw": false,
        "hasCloudflare": false,
        "sourceCodeUrl": "https://raw.githubusercontent.com/vuongvan/mangayomi-swak-extensions/refs/heads/main/javascript/manga/src/ja/weloma.js",
        "apiUrl": "",
        "version": "1.0.0",
        "isManga": true,
        "itemType": 0,
        "isFullData": false,
        "appMinVerReq": "0.5.0",
        "additionalParams": "",
        "sourceCodeLanguage": 1,
        "notes": ""
    }
]